agent_sphere/__init__.py
agent_sphere/charts.py
agent_sphere/code_interpreter_async.py
agent_sphere/code_interpreter_sync.py
agent_sphere/constants.py
agent_sphere/exceptions.py
agent_sphere/models.py
agent_sphere_base/__init__.py
agent_sphere_base/api/__init__.py
agent_sphere_base/api/client/__init__.py
agent_sphere_base/api/client/api/__init__.py
agent_sphere_base/api/client/api/sandboxes/__init__.py
agent_sphere_base/api/client/api/sandboxes/delete_sandboxes_sandbox_id.py
agent_sphere_base/api/client/api/sandboxes/get_sandboxes.py
agent_sphere_base/api/client/api/sandboxes/get_sandboxes_metrics.py
agent_sphere_base/api/client/api/sandboxes/get_sandboxes_sandbox_id.py
agent_sphere_base/api/client/api/sandboxes/get_sandboxes_sandbox_id_logs.py
agent_sphere_base/api/client/api/sandboxes/get_sandboxes_sandbox_id_metrics.py
agent_sphere_base/api/client/api/sandboxes/get_v2_sandboxes.py
agent_sphere_base/api/client/api/sandboxes/post_sandboxes.py
agent_sphere_base/api/client/api/sandboxes/post_sandboxes_sandbox_id_pause.py
agent_sphere_base/api/client/api/sandboxes/post_sandboxes_sandbox_id_refreshes.py
agent_sphere_base/api/client/api/sandboxes/post_sandboxes_sandbox_id_resume.py
agent_sphere_base/api/client/api/sandboxes/post_sandboxes_sandbox_id_timeout.py
agent_sphere_base/api/client/client.py
agent_sphere_base/api/client/errors.py
agent_sphere_base/api/client/models/__init__.py
agent_sphere_base/api/client/models/created_access_token.py
agent_sphere_base/api/client/models/created_team_api_key.py
agent_sphere_base/api/client/models/error.py
agent_sphere_base/api/client/models/listed_sandbox.py
agent_sphere_base/api/client/models/new_access_token.py
agent_sphere_base/api/client/models/new_sandbox.py
agent_sphere_base/api/client/models/new_team_api_key.py
agent_sphere_base/api/client/models/node.py
agent_sphere_base/api/client/models/node_detail.py
agent_sphere_base/api/client/models/node_status.py
agent_sphere_base/api/client/models/node_status_change.py
agent_sphere-0.1.1.dist-info/LICENSE
agent_sphere-0.1.1.dist-info/METADATA
agent_sphere-0.1.1.dist-info/WHEEL
agent_sphere-0.1.1.dist-info/RECORD
