Metadata-Version: 2.3
Name: agent_sphere
Version: 0.1.1
Summary: agent-sphere agents runtime environments
License: MIT
Author: agent-sphere
Requires-Python: >=3.9,<4.0
Classifier: License :: OSI Approved :: MIT License
Classifier: Programming Language :: Python :: 3
Classifier: Programming Language :: Python :: 3.9
Classifier: Programming Language :: Python :: 3.10
Classifier: Programming Language :: Python :: 3.11
Classifier: Programming Language :: Python :: 3.12
Classifier: Programming Language :: Python :: 3.13
Requires-Dist: attrs (>=23.2.0)
Requires-Dist: httpcore (>=1.0.5,<2.0.0)
Requires-Dist: httpx (>=0.27.0,<1.0.0)
Requires-Dist: packaging (>=24.1)
Requires-Dist: protobuf (>=5.29.4,<6.0.0)
Requires-Dist: python-dateutil (>=2.8.2)
Requires-Dist: typing-extensions (>=4.1.0)
Project-URL: Bug Tracker, https://github.com/agent-sphere/python-sdk/issues
Project-URL: Homepage, https://agentsphere.run/
Project-URL: Repository, https://github.com/isoftstone-data-intelligence-ai/AgentSphere-Python-SDK.git
